lbl_profiler/__init__.py
lbl_profiler/custom_trace.py
lbl_profiler/line_stat_tree.py
lbl_profiler/terminal_ui.py
lbl_profiler-0.1.1.dist-info/METADATA
lbl_profiler-0.1.1.dist-info/WHEEL
lbl_profiler-0.1.1.dist-info/top_level.txt
lbl_profiler-0.1.1.dist-info/RECORD
