Metadata-Version: 2.4
Name: lbl_profiler
Version: 0.1.1
Summary: Line by line terminal based profiler
Author-email: Paul <paul.pro@gmail.com>
License: MIT
Classifier: Programming Language :: Python :: 3
Classifier: License :: OSI Approved :: MIT License
Classifier: Operating System :: OS Independent
Requires-Python: >=3.8
